README.txt
setup.py
examples/bridge.py
examples/sunrise.py
pylifx/__init__.py
pylifx/networking.py
pylifx/packet.py
pylifx/scene.py
pylifx.egg-info/PKG-INFO
pylifx.egg-info/SOURCES.txt
pylifx.egg-info/dependency_links.txt
pylifx.egg-info/requires.txt
pylifx.egg-info/top_level.txt