Metadata-Version: 1.1
Name: pylifx
Version: 0.0.3
Summary: A Python library to control and monitor LIFX bulbs
Home-page: https://pypi.python.org/pypi/pylifx
Author: Deryck Arnold
Author-email: derkarnold@gmail.com
License: BSD
Keywords: lifx,smart,light,bulb
Platform: UNKNOWN
Classifier: Development Status :: 3 - Alpha
Classifier: Topic :: Utilities
Classifier: License :: OSI Approved :: Attribution Assurance License
